fpga/digikey-tutorial/part4/button_counter.v
module button_counter(
    
    // inputs
    input wire [1:0] but,


    // outputs
    output reg [2:0] led
);

    wire rst;
    wire clk; 
    
    assign rst = ~but[1];
    assign clk = ~but[0];

    always @ (posedge clk or posedge rst) begin
        if (rst == 1'b1) begin
            led <= 3'b111;
        end else begin
            led <= led + 3'b001;
        end
    end

endmodule

fpga/digikey-tutorial/part4/button_counter_tb.v
`define DUMPSTR(x) `"x.vcd`"
`timescale 1 ns / 10ps

module button_counter_tb();

//-- Leds port
wire [2:0] LED;
reg [1:0] BUT;

localparam DURATION = 100;

//-- Instantiate the unit to test
button_counter UUT (
           .but(BUT),
           .led(LED)
         );

initial begin
  // Time Changes
  BUT = 2'b11; #5;
  BUT = 2'b10; #5;
  BUT = 2'b11; #5;
  BUT = 2'b10; #5;
  BUT = 2'b11; #5;
  BUT = 2'b10; #5;
  BUT = 2'b11; #5;
  BUT = 2'b10; #5;
  BUT = 2'b11; #5;
  BUT = 2'b11; #5;
  BUT = 2'b10; #5;
  BUT = 2'b11; #5;
  BUT = 2'b10; #5;
end

initial begin

  $dumpfile(`DUMPSTR(`VCD_OUTPUT));
  $dumpvars(0, button_counter_tb);

  #(DURATION) $display("End of simulation");
  $finish;
end

endmodule

fpga/digikey-tutorial/part4/button_counter_tb.vcd
$date
	Mon Sep 26 00:12:19 2022
$end
$version
	Icarus Verilog
$end
$timescale
	1ps
$end
$scope module button_counter_tb $end
$var wire 3 ! LED [2:0] $end
$var reg 2 " BUT [1:0] $end
$scope module UUT $end
$var wire 2 # but [1:0] $end
$var wire 1 $ clk $end
$var wire 1 % rst $end
$var reg 3 & led [2:0] $end
$upscope $end
$upscope $end
$enddefinitions $end
#0
$dumpvars
bx &
0%
0$
b11 #
b11 "
bx !
$end
#5000
1$
b10 "
b10 #
#10000
0$
b11 "
b11 #
#15000
1$
b10 "
b10 #
#20000
0$
b11 "
b11 #
#25000
1$
b10 "
b10 #
#30000
0$
b11 "
b11 #
#35000
1$
b10 "
b10 #
#40000
0$
b11 "
b11 #
#50000
1$
b10 "
b10 #
#55000
0$
b11 "
b11 #
#60000
1$
b10 "
b10 #
