fpga/digikey-tutorial/part3/full_sum.v
module full_sum(

    // Inputs
    input wire A,
    input wire B,
    input wire C_IN,

    // Ouputs
    output wire S,
    output wire C_OUT
);


// build sum
wire A_XOR_B;
assign A_XOR_B = A ^ B;
assign S = C_IN ^ A_XOR_B;

// build carry
assign C_OUT = (A & B) | (C_IN & A_XOR_B);

endmodule

fpga/digikey-tutorial/part3/fuil_sum_tb.v
`define DUMPSTR(x) `"x.vcd`"
`timescale 1 ns / 10ps

module full_sum_tb();

//-- Leds port
wire _C_OUT, _S;
reg _C_IN, _A, _B;

localparam DURATION = 60;

//-- Instantiate the unit to test
full_sum UUT (
           .A(_A),
           .B(_B),
           .C_IN(_C_IN),
           .S(_S),
           .C_OUT(_C_OUT)
         );

initial begin

  // Time Changes
  _A = 0; _B = 0; _C_IN=0; #5;
  _A = 0; _B = 0; _C_IN=1; #5;
  _A = 0; _B = 1; _C_IN=0; #5;
  _A = 0; _B = 1; _C_IN=1; #5;
  _A = 1; _B = 0; _C_IN=0; #5;
  _A = 1; _B = 0; _C_IN=1; #5;
  _A = 1; _B = 1; _C_IN=0; #5;
  _A = 1; _B = 1; _C_IN=1; #5;

end

initial begin

  $dumpfile(`DUMPSTR(`VCD_OUTPUT));
  $dumpvars(0, full_sum_tb);

  #(DURATION) $display("End of simulation");
  $finish;
end

endmodule

fpga/digikey-tutorial/part3/and_gate.v
module and_gate(

    // Inputs
    input wire [1:0] BUT,

    // Ouputs
    output wire [2:0] LED
);

    assign LED[0] = ~BUT[0];

endmodule

fpga/digikey-tutorial/part3/and_gate_tb.v
`define DUMPSTR(x) `"x.vcd`"
`timescale 1 ns / 10ps

module and_gate_tb();

//-- Leds port
wire [2:0] _LED;
reg [1:0] _BUT;

localparam DURATION = 1000;

//-- Instantiate the unit to test
and_gate UUT (
           .BUT(_BUT),
           .LED(_LED)
         );

initial begin
  // Time Changes
  _BUT[0] = 0;
  #10 _BUT[0] = 1;
  #20 _BUT[0] = 0;
  #30 _BUT[0] = 1;
end

initial begin

  $dumpfile(`DUMPSTR(`VCD_OUTPUT));
  $dumpvars(0, and_gate_tb);

  #(DURATION) $display("End of simulation");
  $finish;
end

endmodule

fpga/digikey-tutorial/part3/and_gate_tb.vcd
$date
	Tue Sep 27 20:10:10 2022
$end
$version
	Icarus Verilog
$end
$timescale
	1ps
$end
$scope module and_gate_tb $end
$var wire 3 ! _LED [2:0] $end
$var reg 2 " _BUT [1:0] $end
$scope module UUT $end
$var wire 2 # BUT [1:0] $end
$var wire 3 $ LED [2:0] $end
$upscope $end
$upscope $end
$scope module full_sum_tb $end
$var wire 1 % _S $end
$var wire 1 & _C_OUT $end
$var reg 1 ' _A $end
$var reg 1 ( _B $end
$var reg 1 ) _C_IN $end
$scope module UUT $end
$var wire 1 ' A $end
$var wire 1 * A_XOR_B $end
$var wire 1 ( B $end
$var wire 1 ) C_IN $end
$var wire 1 & C_OUT $end
$var wire 1 % S $end
$upscope $end
$upscope $end
$enddefinitions $end
#0
$dumpvars
0*
0)
0(
0'
0&
0%
b0 $
bx0 #
bx0 "
b0 !
$end
#5000
1%
1)
#10000
1*
0)
1(
bx1 "
bx1 #
#15000
1&
0%
1)
#20000
0&
1%
0)
0(
1'
#25000
1&
0%
1)
#30000
0*
0)
1(
bx0 "
bx0 #
#35000
1%
1)
#60000
bx1 "
bx1 #
